baselines/__init__.py
baselines/logger.py
baselines/common/__init__.py
baselines/common/atari_wrappers_deprecated.py
baselines/common/azure_utils.py
baselines/common/misc_util.py
baselines/common/schedules.py
baselines/common/segment_tree.py
baselines/common/tf_util.py
baselines/deepq/__init__.py
baselines/deepq/build_graph.py
baselines/deepq/models.py
baselines/deepq/replay_buffer.py
baselines/deepq/simple.py
baselines/deepq/experiments/__init__.py
baselines/deepq/experiments/custom_cartpole.py
baselines/deepq/experiments/enjoy_cartpole.py
baselines/deepq/experiments/enjoy_pong.py
baselines/deepq/experiments/train_cartpole.py
baselines/deepq/experiments/train_pong.py
baselines/deepq/experiments/atari/__init__.py
baselines/deepq/experiments/atari/download_model.py
baselines/deepq/experiments/atari/enjoy.py
baselines/deepq/experiments/atari/model.py
baselines/deepq/experiments/atari/train.py
baselines/deepq/experiments/atari/wang2015_eval.py
baselines-0.1.4.dist-info/DESCRIPTION.rst
baselines-0.1.4.dist-info/METADATA
baselines-0.1.4.dist-info/RECORD
baselines-0.1.4.dist-info/WHEEL
baselines-0.1.4.dist-info/metadata.json
baselines-0.1.4.dist-info/top_level.txt
