Metadata-Version: 2.0
Name: baselines
Version: 0.1.4
Summary: OpenAI baselines: high quality implementations of reinforcement learning algorithms
Home-page: https://github.com/openai/baselines
Author: OpenAI
Author-email: gym@openai.com
License: UNKNOWN
Platform: UNKNOWN
Requires-Dist: azure (==1.0.3)
Requires-Dist: dill
Requires-Dist: gym (>=0.9.1[all])
Requires-Dist: joblib
Requires-Dist: progressbar2
Requires-Dist: scipy
Requires-Dist: tensorflow (>=1.0.0)
Requires-Dist: tqdm
Requires-Dist: zmq
